setup.py
UNI/Bot.py
UNI/Dynamic_modules.py
UNI/UNI.py
UNI/Uni_cfg.py
UNI/_init_.py
UNI/Bot_Under_Methods/Callback_.py
UNI/Bot_Under_Methods/Chat_.py
UNI/Bot_Under_Methods/File_.py
UNI/Bot_Under_Methods/Inline_.py
UNI/Bot_Under_Methods/Main_.py
UNI/Bot_Under_Methods/Message_.py
UNI/Bot_Under_Methods/Rest_Core.py
UNI/Bot_Under_Methods/__init__.py
UNI/Communicate/__init__.py
UNI/Communicate/handl.py
UNI/Converters/__init__.py
UNI/Converters/primary_converter.py
UNI/Datas/Data.py
UNI/Datas/__init__.py
UNI/Datas/get_data.py
UNI/Datas/process_data.py
UNI/Datas/uni_filters.py
UNI/Sides/__init__.py
UNI/Sides/rest_side.py
UNI/Sides/ssh_side.py
UNI/Types/Custom_Entities_Methods.py
UNI/Types/Custom_Event_Methods.py
UNI/Types/Entities_.py
UNI/Types/Events_.py
UNI/Types/Inline_Result.py
UNI/Types/Keyboards_.py
UNI/Types/Message_Content_.py
UNI/Types/Pack_Events.py
UNI/Types/Reply_.py
UNI/Types/__init__.py
UNI_botcore.egg-info/PKG-INFO
UNI_botcore.egg-info/SOURCES.txt
UNI_botcore.egg-info/dependency_links.txt
UNI_botcore.egg-info/not-zip-safe
UNI_botcore.egg-info/top_level.txt