Metadata-Version: 2.1
Name: UNI_botcore
Version: 1.35
Summary: TELEGRAM BOT API CORE
Author-email: dev.nevermore696@gmail.com
